{
  "$schema": "http://json-schema.org/draft-07/schema",
  "$id": "SchematicsAngularSchematic",
  "title": "Angular Schematic Options Schema",
  "type": "object",
  "description": "Creates a new, generic schematic in the given or default project.",
  "additionalProperties": false,
  "properties": {
    "path": {
      "type": "string",
      "format": "path",
      "description": "The path at which to create the schematic file, relative to the current workspace. Default is a folder with the same name as the schematic in the project root.",
      "visible": false
    },
    "project": {
      "type": "string",
      "description": "The name of the project.",
      "$default": {
        "$source": "projectName"
      }
    },
    "name": {
      "type": "string",
      "description": "The name of the schematic.",
      "$default": {
        "$source": "argv",
        "index": 0
      },
      "x-prompt": "What name would you like to use for the schematic?"
    },
    "type": {
      "type": "string",
      "description": "The type of the schematic.",
      "enum": [
        "Generate",
        "Update",
        "Add"
      ],
      "x-prompt": "Which schematic type would you like to generate?"
    },
    "skipTests": {
      "type": "boolean",
      "description": "Do not create \"spec.ts\" test files for the new schematic.",
      "default": false,
      "x-user-analytics": 12
    },
    "flat": {
      "type": "boolean",
      "description": "Create the new files at the top level of the current project.",
      "default": false
    }
  },
  "required": ["name", "type"]
}
